process_sanskrit/__init__.py
process_sanskrit/functions/SQLiteFind.py
process_sanskrit/functions/__init__.py
process_sanskrit/functions/cleanResults.py
process_sanskrit/functions/compoundAnalysis.py
process_sanskrit/functions/dictionaryLookup.py
process_sanskrit/functions/enhancedSandhiSplitter.py
process_sanskrit/functions/hybridSplitter.py
process_sanskrit/functions/inflect.py
process_sanskrit/functions/model_inference.py
process_sanskrit/functions/process.py
process_sanskrit/functions/processBYT5.py
process_sanskrit/functions/rootAnyWord.py
process_sanskrit/functions/sandhiSplitScorer.py
process_sanskrit/resources/MWKeysOnly.json
process_sanskrit/resources/__init__.py
process_sanskrit/resources/dictionary_references.json
process_sanskrit/resources/stopwords.csv
process_sanskrit/resources/type_map.tsv
process_sanskrit/setup/updateDB.py
process_sanskrit/utils/__init__.py
process_sanskrit/utils/databaseSetup.py
process_sanskrit/utils/detectTransliteration.py
process_sanskrit/utils/dictionary_references.py
process_sanskrit/utils/lexicalResources.py
process_sanskrit/utils/loadResources.py
process_sanskrit/utils/processAPI.py
process_sanskrit/utils/stopwordsRemoval.py
process_sanskrit/utils/transliterationUtils.py
process_sanskrit-1.0.27.dist-info/licenses/LICENSE.md
process_sanskrit-1.0.27.dist-info/METADATA
process_sanskrit-1.0.27.dist-info/WHEEL
process_sanskrit-1.0.27.dist-info/entry_points.txt
process_sanskrit-1.0.27.dist-info/top_level.txt
process_sanskrit-1.0.27.dist-info/RECORD
