Metadata-Version: 2.4
Name: process-sanskrit
Version: 1.0.27
Summary: Process-Sanskrit is python library for automatic Sanskrit text annotation and inflected dictionary search
Author-email: Giacomo De Luca <giacomo.deluca@hotmail.it>
Project-URL: Repository, https://github.com/Giacomo-De-Luca/Process-Sanskrit
Requires-Python: >=3.8
License-File: LICENSE.md
Requires-Dist: requests>=2.20.0
Requires-Dist: sqlalchemy>=1.4.0
Requires-Dist: indic_transliteration>=2.0.0
Requires-Dist: regex>=2022.0.0
Requires-Dist: python-dotenv>=0.19.0
Requires-Dist: sanskrit-parser==0.2.6
Provides-Extra: gensim
Requires-Dist: gensim>=4.0.0; extra == "gensim"
Requires-Dist: sentencepiece>=0.1.95; extra == "gensim"
Provides-Extra: byt5
Requires-Dist: torch>=1.9.0; extra == "byt5"
Requires-Dist: transformers>=4.5.0; extra == "byt5"
Requires-Dist: numpy>=2.0.0; extra == "byt5"
Requires-Dist: scipy>=1.13.0; extra == "byt5"
Dynamic: license-file
